ApiBot/.gitignore
ApiBot/LICENSE
ApiBot/OdooBotAPI.py
ApiBot/README.md
ApiBot/__init__.py
ApiBot/venv/pyvenv.cfg
ApiBot/venv/Lib/site-packages/distutils-precedence.pth
ApiBot/venv/Lib/site-packages/Flask-2.3.2.dist-info/INSTALLER
ApiBot/venv/Lib/site-packages/Flask-2.3.2.dist-info/LICENSE.rst
ApiBot/venv/Lib/site-packages/Flask-2.3.2.dist-info/METADATA
ApiBot/venv/Lib/site-packages/Flask-2.3.2.dist-info/RECORD
ApiBot/venv/Lib/site-packages/Flask-2.3.2.dist-info/WHEEL
ApiBot/venv/Lib/site-packages/Flask-2.3.2.dist-info/entry_points.txt
ApiBot/venv/Lib/site-packages/Flask-2.3.2.dist-info/top_level.txt
ApiBot/venv/Lib/site-packages/Flask_JWT_Extended-4.5.2.dist-info/INSTALLER
ApiBot/venv/Lib/site-packages/Flask_JWT_Extended-4.5.2.dist-info/LICENSE
ApiBot/venv/Lib/site-packages/Flask_JWT_Extended-4.5.2.dist-info/METADATA
ApiBot/venv/Lib/site-packages/Flask_JWT_Extended-4.5.2.dist-info/RECORD
ApiBot/venv/Lib/site-packages/Flask_JWT_Extended-4.5.2.dist-info/REQUESTED
ApiBot/venv/Lib/site-packages/Flask_JWT_Extended-4.5.2.dist-info/WHEEL
ApiBot/venv/Lib/site-packages/Flask_JWT_Extended-4.5.2.dist-info/top_level.txt
ApiBot/venv/Lib/site-packages/Jinja2-3.1.2.dist-info/INSTALLER
ApiBot/venv/Lib/site-packages/Jinja2-3.1.2.dist-info/LICENSE.rst
ApiBot/venv/Lib/site-packages/Jinja2-3.1.2.dist-info/METADATA
ApiBot/venv/Lib/site-packages/Jinja2-3.1.2.dist-info/RECORD
ApiBot/venv/Lib/site-packages/Jinja2-3.1.2.dist-info/WHEEL
ApiBot/venv/Lib/site-packages/Jinja2-3.1.2.dist-info/entry_points.txt
ApiBot/venv/Lib/site-packages/Jinja2-3.1.2.dist-info/top_level.txt
ApiBot/venv/Lib/site-packages/MarkupSafe-2.1.3.dist-info/INSTALLER
ApiBot/venv/Lib/site-packages/MarkupSafe-2.1.3.dist-info/LICENSE.rst
ApiBot/venv/Lib/site-packages/MarkupSafe-2.1.3.dist-info/METADATA
ApiBot/venv/Lib/site-packages/MarkupSafe-2.1.3.dist-info/RECORD
ApiBot/venv/Lib/site-packages/MarkupSafe-2.1.3.dist-info/WHEEL
ApiBot/venv/Lib/site-packages/MarkupSafe-2.1.3.dist-info/top_level.txt
ApiBot/venv/Lib/site-packages/PyJWT-2.8.0.dist-info/AUTHORS.rst
ApiBot/venv/Lib/site-packages/PyJWT-2.8.0.dist-info/INSTALLER
ApiBot/venv/Lib/site-packages/PyJWT-2.8.0.dist-info/LICENSE
ApiBot/venv/Lib/site-packages/PyJWT-2.8.0.dist-info/METADATA
ApiBot/venv/Lib/site-packages/PyJWT-2.8.0.dist-info/RECORD
ApiBot/venv/Lib/site-packages/PyJWT-2.8.0.dist-info/WHEEL
ApiBot/venv/Lib/site-packages/PyJWT-2.8.0.dist-info/top_level.txt
ApiBot/venv/Lib/site-packages/Werkzeug-2.3.6.dist-info/INSTALLER
ApiBot/venv/Lib/site-packages/Werkzeug-2.3.6.dist-info/LICENSE.rst
ApiBot/venv/Lib/site-packages/Werkzeug-2.3.6.dist-info/METADATA
ApiBot/venv/Lib/site-packages/Werkzeug-2.3.6.dist-info/RECORD
ApiBot/venv/Lib/site-packages/Werkzeug-2.3.6.dist-info/WHEEL
ApiBot/venv/Lib/site-packages/Werkzeug-2.3.6.dist-info/top_level.txt
ApiBot/venv/Lib/site-packages/_distutils_hack/__init__.py
ApiBot/venv/Lib/site-packages/_distutils_hack/override.py
ApiBot/venv/Lib/site-packages/blinker/__init__.py
ApiBot/venv/Lib/site-packages/blinker/_saferef.py
ApiBot/venv/Lib/site-packages/blinker/_utilities.py
ApiBot/venv/Lib/site-packages/blinker/base.py
ApiBot/venv/Lib/site-packages/blinker/py.typed
ApiBot/venv/Lib/site-packages/blinker-1.6.2.dist-info/INSTALLER
ApiBot/venv/Lib/site-packages/blinker-1.6.2.dist-info/LICENSE.rst
ApiBot/venv/Lib/site-packages/blinker-1.6.2.dist-info/METADATA
ApiBot/venv/Lib/site-packages/blinker-1.6.2.dist-info/RECORD
ApiBot/venv/Lib/site-packages/blinker-1.6.2.dist-info/WHEEL
ApiBot/venv/Lib/site-packages/blinker-1.6.2.dist-info/top_level.txt
ApiBot/venv/Lib/site-packages/click/__init__.py
ApiBot/venv/Lib/site-packages/click/_compat.py
ApiBot/venv/Lib/site-packages/click/_termui_impl.py
ApiBot/venv/Lib/site-packages/click/_textwrap.py
ApiBot/venv/Lib/site-packages/click/_winconsole.py
ApiBot/venv/Lib/site-packages/click/core.py
ApiBot/venv/Lib/site-packages/click/decorators.py
ApiBot/venv/Lib/site-packages/click/exceptions.py
ApiBot/venv/Lib/site-packages/click/formatting.py
ApiBot/venv/Lib/site-packages/click/globals.py
ApiBot/venv/Lib/site-packages/click/parser.py
ApiBot/venv/Lib/site-packages/click/py.typed
ApiBot/venv/Lib/site-packages/click/shell_completion.py
ApiBot/venv/Lib/site-packages/click/termui.py
ApiBot/venv/Lib/site-packages/click/testing.py
ApiBot/venv/Lib/site-packages/click/types.py
ApiBot/venv/Lib/site-packages/click/utils.py
ApiBot/venv/Lib/site-packages/click-8.1.6.dist-info/INSTALLER
ApiBot/venv/Lib/site-packages/click-8.1.6.dist-info/LICENSE.rst
ApiBot/venv/Lib/site-packages/click-8.1.6.dist-info/METADATA
ApiBot/venv/Lib/site-packages/click-8.1.6.dist-info/RECORD
ApiBot/venv/Lib/site-packages/click-8.1.6.dist-info/WHEEL
ApiBot/venv/Lib/site-packages/click-8.1.6.dist-info/top_level.txt
ApiBot/venv/Lib/site-packages/colorama/__init__.py
ApiBot/venv/Lib/site-packages/colorama/ansi.py
ApiBot/venv/Lib/site-packages/colorama/ansitowin32.py
ApiBot/venv/Lib/site-packages/colorama/initialise.py
ApiBot/venv/Lib/site-packages/colorama/win32.py
ApiBot/venv/Lib/site-packages/colorama/winterm.py
ApiBot/venv/Lib/site-packages/colorama/tests/__init__.py
ApiBot/venv/Lib/site-packages/colorama/tests/ansi_test.py
ApiBot/venv/Lib/site-packages/colorama/tests/ansitowin32_test.py
ApiBot/venv/Lib/site-packages/colorama/tests/initialise_test.py
ApiBot/venv/Lib/site-packages/colorama/tests/isatty_test.py
ApiBot/venv/Lib/site-packages/colorama-0.4.6.dist-info/INSTALLER
ApiBot/venv/Lib/site-packages/colorama-0.4.6.dist-info/METADATA
ApiBot/venv/Lib/site-packages/colorama-0.4.6.dist-info/RECORD
ApiBot/venv/Lib/site-packages/colorama-0.4.6.dist-info/WHEEL
ApiBot/venv/Lib/site-packages/colorama-0.4.6.dist-info/licenses/LICENSE.txt
ApiBot/venv/Lib/site-packages/itsdangerous-2.1.2.dist-info/INSTALLER
ApiBot/venv/Lib/site-packages/itsdangerous-2.1.2.dist-info/LICENSE.rst
ApiBot/venv/Lib/site-packages/itsdangerous-2.1.2.dist-info/METADATA
ApiBot/venv/Lib/site-packages/itsdangerous-2.1.2.dist-info/RECORD
ApiBot/venv/Lib/site-packages/itsdangerous-2.1.2.dist-info/WHEEL
